{
  "id": "feature-fast",
  "name": "Feature Development (Fast)",
  "description": "Full pipeline with plan review in review-and-edit mode and learn stage enabled. Higher retry limits for complex features. The plan reviewer can directly edit the plan, shortcutting the review-revise loop.",
  "builtin": true,
  "created_at": "2026-05-29T00:00:00Z",
  "tags": [
    "full-pipeline",
    "plan-review",
    "plan-edit",
    "learn"
  ],
  "config": {
    "stages": {
      "plan": {
        "agent": "planner",
        "enabled": true
      },
      "coordinate": {
        "agent": "coordinator",
        "enabled": true
      },
      "implement": {
        "agent": "implementer",
        "enabled": true
      },
      "test": {
        "agent": "tester",
        "enabled": true
      },
      "review": {
        "agent": "reviewer",
        "enabled": true
      },
      "pr": {
        "agent": "guardian",
        "enabled": true
      },
      "learn": {
        "agent": "learner",
        "enabled": true
      },
      "plan_review": {
        "agent": "plan_reviewer",
        "enabled": true,
        "mode": "review_and_edit"
      }
    },
    "loops": {
      "implement_test": 10,
      "pr_changes": 5,
      "restart_planning": 3,
      "plan_review": 3
    },
    "effort": {
      "auto_mode": "adaptive",
      "auto_cap": "xhigh"
    },
    "agents": {
      "planner": {
        "model": "opus",
        "max_turns": 100,
        "effort": "xhigh"
      },
      "coordinator": {
        "model": "opus",
        "max_turns": 300,
        "effort": "high"
      },
      "implementer": {
        "model": "sonnet",
        "max_turns": 300
      },
      "tester": {
        "model": "sonnet",
        "max_turns": 100
      },
      "reviewer": {
        "model": "opus",
        "max_turns": 50,
        "effort": "high"
      },
      "guardian": {
        "model": "opus",
        "max_turns": 50,
        "effort": "high"
      },
      "learner": {
        "model": "opus",
        "max_turns": 50
      },
      "plan_reviewer": {
        "model": "opus",
        "max_turns": 50,
        "effort": "high"
      }
    },
    "circuit_breaker": {
      "enabled": true,
      "max_consecutive_failures": 3,
      "transient_retry_count": 3,
      "transient_retry_backoff_seconds": [
        10,
        30,
        90
      ]
    },
    "milestones": {
      "plan_approval": true,
      "pr_approval": false,
      "deploy_approval": false
    }
  }
}
